{
  "startDate": "日期",
  "workstation": "工位号",
  "productModel": "产品型号",
  "red": "红色",
  "blue": "蓝色",
  "infrared": "红外",
  "red2": "红色2",
  "blue2": "蓝色2",
  "infrared2": "红外2",
  "udiCode": "UDI码",
  "lampBoardQrCode": "灯板二维码",
  "batteryCellCode": "电芯码",
  "chargingBoardPcbaCode": "充电板PCBA码",
  "maskPcbaCode": "面罩PCBA码",
  "controllerPcbaCode": "手控器PCBA码",
  "controllerSoftwareVersion": "手控器软件版本",
  "maskSoftwareVersion": "面罩软件版本",
  "controllerFactoryQrCode": "手控器出厂二维码",
  "faceDetectionProgramVersion": "面部探测程序版本",
  "circuitFaultCode": "电路故障码",
  "redLightWavelength": "红灯波长",
  "blueLightWavelength": "蓝灯波长",
  "infraredLightWavelength": "红外灯波长",
  "redLightCurrent": "红灯电流",
  "blueLightCurrent": "蓝灯电流",
  "infraredLightCurrent": "红外灯电流",
  "msiLightCurrent": "MSI灯电流",
  "fanCurrent": "风扇电流",
  "batteryVoltage": "电池电压",
  "dischargeCurrent": "放电电流",
  "batteryPower": "电池电量",
  "faceSensorStatus": "面部传感器状态",
  "faceSensorValue": "面部传感器值",
  "batteryCell1Voltage": "电芯1电压",
  "batteryCell2Voltage": "电芯2电压",
  "productNtc1TemperatureStart": "产品NTC1温度S",
  "productNtc1TemperatureEnd": "产品NTC1温度E",
  "productNtc2TemperatureStart": "产品NTC2温度S",
  "productNtc2TemperatureEnd": "产品NTC2温度E",
  "instrumentNtc1TemperatureStart": "仪表NTC1温度S",
  "instrumentNtc1TemperatureEnd": "仪表NTC1温度E",
  "instrumentNtc2TemperatureStart": "仪表NTC2温度S",
  "instrumentNtc2TemperatureEnd": "仪表NTC2温度E",
  "productNtc1Difference": "产品NTC1差值",
  "productNtc2Difference": "产品NTC2差值",
  "instrumentNtc1Difference": "仪表NTC1差值",
  "instrumentNtc2Difference": "仪表NTC2差值",
  "productNtcDifferenceStart": "产品NTC差值S",
  "productNtcDifferenceEnd": "产品NTC差值E",
  "instrumentNtcDifferenceStart": "仪表NTC差值S",
  "instrumentNtcDifferenceEnd": "仪表NTC差值E",
  "chargingStatus": "充电状态",
  "chargingVoltage": "充电电压",
  "chargingCurrent": "充电电流",
  "instrumentChargingCurrent": "仪表充电电流",
  "chargingCurrentDifference": "充电电流差值",
  "instrumentNtcDifferenceBeforeCooling": "仪器NTC1和NTC2的差值(制冷前)",
  "productAndInstrumentNtc1Difference": "产品NTC1和仪器NTC1差值",
  "productAndInstrumentNtc2Difference": "产品NTC2和仪器NTC2差值",
  "coolingStatus": "制冷状态",
  "coolingSetTemperature": "制冷设置温度",
  "chargingTest": "充电测试",
  "withstandVoltageTest": "耐压测试",
  "cellCode": "电芯码",
  "handheldControllerPcbaCode": "手控器PCBA码",
  "handheldSoftwareVersion": "手控器软件版本",
  "handheldFactoryQrCode": "手控器出厂二维码",
  "batteryCapacity": "电池电量",
  "cell1Voltage": "电芯1电压",
  "cell2Voltage": "电芯2电压",
  "productNtc1TempS": "产品NTC1温度S",
  "productNtc1TempE": "产品NTC1温度E",
  "productNtc2TempS": "产品NTC2温度S",
  "productNtc2TempE": "产品NTC2温度E",
  "meterNtc1TempS": "仪表NTC1温度S",
  "meterNtc1TempE": "仪表NTC1温度E",
  "meterNtc2TempS": "仪表NTC2温度S",
  "meterNtc2TempE": "仪表NTC2温度E",
  "meterNtc1Difference": "仪表NTC1差值",
  "meterNtc2Difference": "仪表NTC2差值",
  "productNtcDifferenceS": "产品NTC差值S",
  "productNtcDifferenceE": "产品NTC差值E",
  "meterNtcDifferenceS": "仪表NTC差值S",
  "meterNtcDifferenceE": "仪表NTC差值E",
  "meterChargingCurrent": "仪表充电电流",
  "weight": "称重重量",
  "lineNumber": "线体",
  "showSerialNo": "0.4 SHOW SERIALNO 显示序列号",
  "chkPowerOn": "A1.0 CHK POWER ON ATE 上电开机",
  "enterDebugMode": "A1.1 ENTER DEBUG MODE 进入调试模式",
  "showReadCellMsg": "A7.7 SHOW READ CELL MSG 显示读取电池消息",
  "showReadMainPcbaMsg": "A7.9 SHOW READ MAIN PCBA MSG 显示读取主PCBA消息",
  "showReadPcba2Msg": "A7.11 SHOW READ PCBA2 MSG 显示读取PCBA2消息",
  "showReadPackMsg": "A7.13 SHOW READ PACK MSG 读取 MCU 遥控器机身码",
  "readAllKeyOff": "A1.2 READ ALL KEY OFF 读取所有按键关闭状态",
  "readK4K5": "A1.3 READ K4 K5 读取 K4 K5 左右键状态",
  "readPotentiometer": "A1.4 READ POTENTIOMETER 检查编码开关",
  "readAllKeyOff2": "A1.5 READ ALL KEY OFF 读取所有按键关闭状态",
  "readPackVol": "A1.10 READ PACK VOL 读取 PACK 总电压",
  "readPackCell1Vol": "A1.12 READ PACK CELL1 VOL 读取 CL1 电压",
  "readPackCell2Vol": "A1.13 READ PACK CELL2 VOL 读取 CL2 电压",
  "chkCellVolDiffMax": "A1.14 CHK CELL VOL DIFF MAX CL1 CL2 压差校验",
  "readNtc": "A1.15 READ NTC 读取 NTC",
  "chkUiVersion": "A1.17 CHK UI VERSION 读取软件版本",
  "discharge1ATestPrepare": "A3.2 DISCHARGE1A TEST PREPARE 放电准备-电子负载恒流 1A，改为 3A",
  "chkBatOutVol": "A3.9 CHK BATOUT VOL 放电 BAT 输出电压",
  "chkDischargeCur": "A3.10 CHK DISCHARGE CUR 负载放电和电子负载电流校验",
  "readDischargeCur": "A3.11 READ DISCHARGE CUR 读取放电电流",
  "readDischargeSta": "A3.11B READ DISCHARGE STA 读取放电状态",
  "dischargeOcpTestPrepare": "A3.12 DISCHARGE OCP TEST PREPARE 过流检查",
  "readDischargeCur2": "A3.13 READ DISCHARGE CUR 读取放电电流",
  "readDischargeSta2": "A3.13B READ DISCHARGE STA 读取放电结束",
  "dischargeTestEnd": "A3.17 DISCHARGE TEST END 放电测试结束",
  "chkUiTx": "A3.22A CHK UI TX 遥控器通讯口校验",
  "chargeTestPrepare": "A6.01 CHARGE TEST PREPARE 2A 适配器充电准备",
  "readChargerVolt": "A6.03 READ CHARGER VOLT 读取充电器电压",
  "readChargeCur": "A6.04 READ CHARGE CUR 读取充电电流",
  "ateChangeCur": "A6.05 ATECHARGE CUR 自检 ATE 充电电流",
  "chkStillChargeCur": "A6.06 CHK STILL CHARGE CUR 充电保持电流",
  "chargeTestEnd": "A6.07 CHARGE TEST END 充电结束",
  "readSoc": "A7.14 READ SOC 读取 SOC",
  "packOff": "A8.0 PACK OFF 遥控器关机",
  "allTestEnd": "A9.0 ALL TEST END 所有测试结束",
  "passFail": "PASS/Fail 测试结果",
  "testTime": "日期",
  "positiveNegativeResult": "正反结果",
  "revolutionSpeedTestValue": "转速测试值",
  "vacuumTestValue": "真空测试值",
  "setBauds": "SetBauds",
  "robotToPhotoPoint": "机器人到拍照点",
  "pressCylinder": "压紧气缸",
  "fakePackageCylinder": "假包气缸",
  "communicationBoardPowered": "通讯板通电",
  "testMode": "测试模式",
  "readMainboardVersion": "读主板版本号",
  "waitForRobotInPlace": "等待机器人到位",
  "screenAllRed": "屏幕全红",
  "allRedCheck": "全红检测",
  "screenAllBlue": "屏幕全蓝",
  "allBlueCheck": "全蓝检测",
  "buttonSilkscreenCheck": "按键丝印检测",
  "powerButtonRelease": "开机按钮松开",
  "gearSwitchButtonRelease": "档位切换按钮松开",
  "dustEmissionIntensity": "灰尘发射强度",
  "dustReceptionIntensity": "灰尘接收强度",
  "robotToGearPoint": "机器人到档位点",
  "dustCylinderOut": "灰尘气缸出",
  "dustCylinderBack": "灰尘气缸回",
  "dustCylinderOut2": "灰尘气缸出",
  "dustCount": "灰尘个数",
  "waitForRobotInPlace2": "等待机器人到位",
  "gearSwitchCylinderOut": "档位切换气缸出",
  "dustReceptionIntensity2": "灰尘接收强度",
  "dustCylinderBack2": "灰尘气缸回",
  "gearSwitchButtonPress": "档位切换按钮按下",
  "gearSwitchCylinderBack": "档位切换气缸回",
  "robotToStandbyPoint": "机器人到待机点",
  "clearLogs": "清除日志",
  "snWrite": "SN写入",
  "snRead": "SN读取",
  "normalMode": "正常模式",
  "communicationBoardPowerOff": "通讯板断电",
  "resetCylinder": "复位气缸",
  "pcScan": "扫码",
  "scanReceiveToPc": "扫码接收至PC",
  "floorBrushDirectionResult": "地刷方向结果",
  "floorBrushVacuumLowValue": "地刷吸尘低值",
  "floorBrushVacuumHighValue": "地刷吸尘高值",
  "floorBrushVacuumMediumValue": "地刷吸尘中值",
  "currentLowValue": "当前低值",
  "currentHighValue": "当前高值",
  "currentMediumValue": "当前中值",
  "testCompleteToPcComplete1EmergencyStop2DevicePopupNoUpload3PcReadTo0": "测试完成至PC，1紧急停止2设备弹出未上传3 PC读至0",
  "floorBrushVacuumLowValueUpperLimit": "地刷吸尘低值上限",
  "floorBrushVacuumLowValueLowerLimit": "地刷吸尘低值下限",
  "floorBrushVacuumHighValueUpperLimit": "地刷吸尘高值上限",
  "floorBrushVacuumHighValueLowerLimit": "地刷吸尘高值下限",
  "floorBrushVacuumMediumValueUpperLimit": "地刷吸尘中值上限",
  "floorBrushVacuumMediumValueLowerLimit": "地刷吸尘中值下限",
  "currentLowValueUpperLimit": "当前低值上限",
  "currentLowValueLowerLimit": "当前低值下限",
  "currentHighValueUpperLimit": "当前高值上限",
  "currentHighValueLowerLimit": "当前高值下限",
  "currentMediumValueUpperLimit": "当前中值上限",
  "currentMediumValueLowerLimit": "当前中值下限",
  "floorBrushVacuumLowTestUse1NotUse0Use": "地刷吸尘低测试使用1不使用0",
  "floorBrushVacuumHighTestUse1NotUse0Use": "地刷吸尘高测试使用1不使用0",
  "floorBrushVacuumMediumTestUse1NotUse0Use": "地刷吸尘中测试使用1不使用0",
  "currentLowTestUse1NotUse0Use": "当前低测试使用1不使用0",
  "currentHighTestUse1NotUse0Use": "当前高测试使用1不使用0",
  "currentMediumTestUse1NotUse0Use": "当前中测试使用1不使用0",
  "floorBrushDirectionUse1NotUse0Use": "地刷方向使用1不使用0",
  "scanReceive1ToPc": "扫码接收至PC",
  "chargingLightStartStatusResult1Ok2Ng": "充电灯启动状态结果1合格2不合格",
  "screenRunningStatusResult1Ok2Ng": "屏幕运行状态结果1合格2不合格",
  "rotationDirectionResult1Ok2Ng": "旋转方向结果1合格2不合格",
  "rotationSpeedRpmIntegerPart": "旋转速度RPM整数部分",
  "stallResult1Ok2Ng": "卡住结果1合格2不合格",
  "chargingLightChargingStatusResult1Ok2Ng": "充电灯充电状态结果1合格2不合格",
  "currentValueAInteger": "电流值A整数",
  "voltageValueVInteger": "电压值V整数",
  "batteryPackVoltageDifferenceVInteger": "电池包电压差V整数",
  "currentUpperLimitInteger": "电流上限整数",
  "currentLowerLimitInteger": "电流下限整数",
  "voltageUpperLimitInteger": "电压上限整数",
  "voltageLowerLimitInteger": "电压下限整数",
  "rotationSpeedUpperLimitInteger": "旋转速度上限整数",
  "rotationSpeedLowerLimitInteger": "旋转速度下限整数",
  "batteryPackVoltageDifferenceUpperLimitInteger": "电池包电压差上限整数",
  "batteryPackVoltageDifferenceLowerLimitInteger": "电池包电压差下限整数",
  "rotationSpeedTestUse1NotUse0Use": "旋转速度测试使用1不使用0",
  "chargingLightStartStatus1NotUse0Use": "充电灯启动状态1不使用0",
  "screenRunningLight1NotUse0Use": "屏幕运行灯1不使用0",
  "stallResult1NotUse0Use": "卡住结果1不使用0",
  "chargingLight1NotUse0Use": "充电灯1不使用0",
  "rotationDirectionResultDirection1NotUse0Use": "旋转方向结果方向1不使用0",
  "chargingCurrentResult1NotUse0Use": "充电电流结果1不使用0",
  "voltage1NotUse0Use": "电压1不使用0",
  "batteryPackVoltageDifference1NotUse0Use": "电池包电压差1不使用0",
  "stall1NotUse0Use": "卡住1不使用0",

  "按钮开机": "按钮开机",
  "SN比对 系统录入": "SN比对 系统录入",
  "通讯barcode比对 CellSerialization[String] = **********************************": "通讯barcode比对 CellSerialization[String] = **********************************",
  "通讯barcode比对 UIPCBACode[String] = **********************************": "通讯barcode比对 UIPCBACode[String] = **********************************",
  "通讯barcode比对 ChargePCBACode[String] = **********************************": "通讯barcode比对 ChargePCBACode[String] = **********************************",
  "DebugMode": "DebugMode",
  "开路电压(OCV)": "开路电压(OCV)",
  "开路电压(OCV) 7V ~ 7·4V": "开路电压(OCV) 7V ~ 7·4V",
  "开路电压(OCV) 电压信号": "开路电压(OCV) 电压信号",
  "开路电压(OCV) 通讯电压误差±200mV": "开路电压(OCV) 通讯电压误差±200mV",
  "开路电压(OCV) 通讯电压误差": "开路电压(OCV) 通讯电压误差",
  "开路电压(OCV) 电芯电压": "开路电压(OCV) 电芯电压",
  "开路电压(OCV) 电芯压差": "开路电压(OCV) 电芯压差",
  "UI Version SoftwareVersion[String] = ****FW300*******WILLOW-2S1P": "UI Version SoftwareVersion[String] = ****FW300*******WILLOW-2S1P",
  "Cell&NTC NTCVoltage[mV,U2] ∈ 800mV ~ 3130mV": "Cell&NTC NTCVoltage[mV,U2] ∈ 800mV ~ 3130mV",
  "Cell&NTC VCell-1[mV,U2] ∈ 3500mV ~ 3700mV": "Cell&NTC VCell-1[mV,U2] ∈ 3500mV ~ 3700mV",
  "Cell&NTC VCell-2[mV,U2] ∈ 3500mV ~ 3700mV": "Cell&NTC VCell-2[mV,U2] ∈ 3500mV ~ 3700mV",
  "放电测试(Discharge)1A X1,P4, Discharge/1A": "放电测试(Discharge)1A X1,P4, Discharge/1A",
  "放电测试(Discharge)1A 量测电流和电压": "放电测试(Discharge)1A 量测电流和电压",
  "放电测试(Discharge)1A 电流 0·8A ~ 1·2A": "放电测试(Discharge)1A 电流 0·8A ~ 1·2A",
  "放电测试(Discharge)1A 电流": "放电测试(Discharge)1A 电流",
  "放电测试(Discharge)1A 电流信号": "放电测试(Discharge)1A 电流信号",
  "放电测试(Discharge)1A 通讯电流误差±190mA": "放电测试(Discharge)1A 通讯电流误差±190mA",
  "过流保护(OCP)8A 单点过流": "过流保护(OCP)8A 单点过流",
  "过流保护(OCP)8A 单点过流P4, Discharge/8A": "过流保护(OCP)8A 单点过流P4, Discharge/8A",
  "过流保护(OCP)8A 保护规格 0·5mS ~ 500mS": "过流保护(OCP)8A 保护规格 0·5mS ~ 500mS",
  "测量电压(V) 电压量测": "测量电压(V) 电压量测",
  "测量电压(V) X1,0V ~ 0·5V": "测量电压(V) X1,0V ~ 0·5V",
  "通讯电流 DischargingCurrent[mA,U2] ∈ 0mA ~ 300mA": "通讯电流 DischargingCurrent[mA,U2] ∈ 0mA ~ 300mA",
  "按住K4K5": "按住K4K5",
  "请先开机,按住K4K5后按下按钮": "请先开机,按住K4K5后按下按钮",
  "通讯K4K5 K4[U2] = 1": "通讯K4K5 K4[U2] = 1",
  "通讯K4K5 K5[U2] = 1": "通讯K4K5 K5[U2] = 1",
  "松开K4K5": "松开K4K5",
  "延时(Delay) 等待1500mS": "延时(Delay) 等待1500mS",
  "延时1": "延时1",
  "旋钮顺时针逆时针并按下按钮": "旋钮顺时针逆时针并按下按钮",
  "旋钮判断 ClockwiseCount[U2] > 0": "旋钮判断 ClockwiseCount[U2] > 0",
  "旋钮判断 CounterclockwiseCount[U2] > 0": "旋钮判断 CounterclockwiseCount[U2] > 0",
  "电源输出": "电源输出",
  "延时2": "延时2",
  "延时(Delay) 等待6000mS": "延时(Delay) 等待6000mS",
  "充电通讯电流电压 ChargerCurrent[mA,U2] ∈ 730mA ~ 950mA": "充电通讯电流电压 ChargerCurrent[mA,U2] ∈ 730mA ~ 950mA",
  "充电通讯电流电压 ChargerVoltage[mV,U2] ∈ 4500mV ~ 5700mV": "充电通讯电流电压 ChargerVoltage[mV,U2] ∈ 4500mV ~ 5700mV",
  "SOC SOC[%,U2] ∈ 33% ~ 47%": "SOC SOC[%,U2] ∈ 33% ~ 47%",
  "SOC SOC[%,U2] ∈ 35% ~ 43%": "SOC SOC[%,U2] ∈ 35% ~ 43%",
  "交流内阻(ACIR)": "交流内阻(ACIR)",
  "交流内阻(ACIR) 交流内阻": "交流内阻(ACIR) 交流内阻",
  "电源关闭": "电源关闭",
  "延时3": "延时3",
  "延时(Delay) 等待2000mS": "延时(Delay) 等待2000mS",
  "充电测试自检电流 量测电流和电压": "充电测试自检电流 量测电流和电压",
  "充电测试自检电流 X1,P1, Charge/5·7V/2A": "充电测试自检电流 X1,P1, Charge/5·7V/2A",
  "充电测试自检电流 电流": "充电测试自检电流 电流",
  "充电测试自检电流 电流 1·4A ~ 1·9A": "充电测试自检电流 电流 1·4A ~ 1·9A",
  "闭关DebugMode": "闭关DebugMode",

  "vacuumDegree1": "真空度1",
  "vacuumDegree2": "真空度2",
  "vacuumDegree3": "真空度3",
  "vacuumDegree4": "真空度4",
  "flowRate1": "流量1",
  "flowRate2": "流量2",
  "flowRate3": "流量3",
  "inhalationPower1": "吸入功率1",
  "inhalationPower2": "吸入功率2",
  "inhalationPower3": "吸入功率3",
  "protectionVoltage": "保护电压",
  "noLoadVoltage": "空载电压",
  "noLoadPower": "空载功率",
  "loadVoltage": "负载电压",
  "loadCurrent": "负载电流",
  "realTimeSprayFlow": "实时喷雾流量",
  "forwardTestCurrent": "正向测试电流",
  "reverseTestCurrent": "反向测试电流",
  "stallTestCurrent": "卡死测试电流",
  "forwardTestSpeed": "正向测试速度",
  "reverseTestSpeed": "反向测试速度",
  "forwardTestDirection": "正向测试方向",
  "reverseTestDirection": "反向测试方向",
  "time1Voltage": "时间1电压",
  "time2Current": "时间2电流",
  "time2Power": "时间2功率",
  "time2Temperature": "时间2温度",
  "time2Airflow": "时间2气流量",
  "time2WindSpeed": "时间2风速",
  "temperatureDifference": "温差",
  "time2Voltage": "时间2电压",
  "time1Current": "时间1电流",
  "time1Power": "时间1功率",
  "time1Temperature": "时间1温度",
  "time1Airflow": "时间1气流量",
  "time1WindSpeed": "时间1风速",
  "stallTestValue": "堵转测试值",
  "voltageTestValue": "堵转测试值",
  "currentTestValue": "电流测试值",
  "frontLightTest": "前灯测试",
  "heightClearance": "限高离地间隙",
  "lowClearance": "限低离地间隙",
  "positiveNegativeTest": "正反测试",
  "rpmValue": "转速值",

  "weightUnit": "重量单位",

  "powerOnSuctionVoltage": "开机吸口电压",
  "powerOffSuctionVoltage": "关机吸口电压",
  "suctionVoltage": "吸口充电电压",
  "suctionCurrent": "吸口充电电流",
  "batteryChargingVoltage": "电池充电电压",
  "batteryChargingCurrent": "电池充电电流",

  "noLoadInputPower": "空载输入功率",
  "noLoadOutputVoltage": "空载输出电压",
  "loadOutputVoltage": "负载输出电压",
  "loadOutputCurrent": "负载输出电流",

  "groundResistance": "接地电阻",
  "fullCurrent": "全开电流",
  "fullPower": "全开功率",
  "fullAirflow": "全开风量",
  "holeOneAperture": "堵孔一孔径",
  "holeOneCurrent": "堵孔一电流",
  "holeOnePower": "堵孔一功率",
  "holeOneVacuumDegree": "堵孔一真空度",
  "holeOneAirflow": "堵孔一风量",
  "holeOneSafetyValve": "堵孔一",
  "holeOneInletPower": "堵孔一吸入功率",
  "holeOneInletEfficiency": "堵孔一吸入效率",
  "holeTwoAperture": "堵孔二孔径",
  "holeTwoCurrent": "堵孔二电流",
  "holeTwoPower": "堵孔二功率",
  "holeTwoVacuum": "堵孔二真空度",
  "holeTwoAirflow": "堵孔二风量",
  "holeTwoSafetyValve": "堵孔二安全阀",
  "holeTwoInletPower": "堵孔二吸入功率",
  "holeTwoInletEfficiency": "堵孔二吸入效率",
  "holeThreeAperture": "堵孔三孔径",
  "holeThreeCurrent": "堵孔三电流",
  "holeThreePower": "堵孔三功率",
  "holeThreeVacuum": "堵孔三真空度",
  "holeThreeAirflow": "堵孔三风量",
  "holeThreeSafetyValve": "堵孔三安全阀",
  "holeThreeInletPower": "堵孔三吸入功率",
  "holeThreeInletEfficiency": "堵孔三吸入效率",
  "fullStallCurrent": "全堵电流",
  "fullStallPower": "全堵功率",
  "fullVacuum": "全堵真空度",

  "current": "电流",
  "power": "功率",
  "speed": "转速",
  "direction": "转向",
  "vacuum": "真空度",
  "airflow": "风量",
  "inletPower": "吸入功率",
  "inletEfficiency": "吸入效率",

  "SetBauds": "SetBauds",
  "复位气缸": "复位气缸",
  "Delay ms": "Delay ms",
  "Delay ms2": "Delay ms2",
  "Delay ms3": "Delay ms3",
  "Delay ms4": "Delay ms4",
  "复位": "复位",
  "固定气缸": "固定气缸",
  "夹紧气缸": "夹紧气缸",
  "通讯气缸": "通讯气缸",
  "假电池通电": "假电池通电",
  "测试模式": "测试模式",
  "屏幕全红": "屏幕全红",
  "屏幕全红灯环": "屏幕全红灯环",
  "屏幕全蓝": "屏幕全蓝",
  "屏幕全蓝灯环": "屏幕全蓝灯环",
  "屏幕指示图标": "屏幕指示图标",
  "查询屏幕版本": "查询屏幕版本",
  "读主板版本号": "读主板版本号",
  "灰尘发射强度": "灰尘发射强度",
  "灰尘接收强度": "灰尘接收强度",
  "灰尘气缸": "灰尘气缸",
  "灰尘气缸回": "灰尘气缸回",
  "灰尘个数": "灰尘个数",
  "按键未按住": "按键未按住",
  "请按住开机键": "请按住开机键",
  "模式按键未按住": "模式按键未按住",
  "请按住模式键": "请按住模式键",
  "清除日志": "清除日志",
  "SN写入": "SN写入",
  "SN读取": "SN读取",
  "正常模式": "正常模式",
  "假电池断电": "假电池断电",
  "通讯气缸回": "通讯气缸回",
  "夹紧气缸回": "夹紧气缸回",

  "开机气缸": "开机气缸",
  "开机辅助气缸": "开机辅助气缸",
  "开机键按下": "开机键按下",
  "开机辅助气缸回": "开机辅助气缸回",
  "开机气缸回": "开机气缸回",
  "模式按键辅助气缸": "模式按键辅助气缸",
  "模式按键气缸": "模式按键气缸",
  "模式键按下": "模式键按下",
  "模式按键气缸回": "模式按键气缸回",
  "模式按键辅助气缸回": "模式按键辅助气缸回",

  "hostLowGradeValue": "主机低档值",
  "hostHighGradeValue": "主机高档值",
  "currentLowGradeValue": "电流低档值",
  "floorBrushLowGradeUpperLimit": "地刷低档上限",
  "floorBrushLowGradeLowerLimit": "地刷低档下限",
  "floorBrushHighGradeUpperLimit": "地刷高档上限",
  "floorBrushHighGradeLowerLimit": "地刷高档下限",
  "hostLowGradeUpperLimit": "主机低档上限",
  "hostLowGradeLowerLimit": "主机低档下限",
  "hostHighGradeUpperLimit": "主机高档上限",
  "hostHighGradeLowerLimit": "主机高档下限",
  "currentHighGradeLowerLimit": "电流高档下限",

  "lowSpeedValue": "低档转速值",
  "lowPositiveNegativeRotation": "低速正反转",
  "highSpeedValue": "高档转速值",
  "stall": "堵转",
  "batteryPackVoltage": "电池包电压",
  "startLight": "启动灯",
  "chargingLight": "充电灯",
  "lowSpeedUpperLimit": "低档转速上限",
  "lowSpeedLowerLimit": "低档转速下限",
  "highSpeedUpperLimit": "高档转速上限",
  "highSpeedLowerLimit": "高档转速下限",
  "voltageUpperLimit": "电压上限",
  "voltageLowerLimit": "电压下限",
  "currentUpperLimit": "电流上限",
  "currentLowerLimit": "电流下限",
  "lowSpeedUsageSelection": "低档转速使用选择",
  "highSpeedUsageSelection": "高档转速使用选择",
  "stallUsageSelection": "堵转使用选择",
  "voltageUsageSelection": "电压使用选择",
  "currentUsageSelection": "电流使用选择",
  "startLightSelection": "启动灯使用选择",
  "chargingLightSelection": "充电灯使用选择",

  "放电电源输出": "放电电源输出",
  "放电延时": "放电延时",
  "放电电压(V) 电压量测": "放电电压(V) 电压量测",
  "放电电流(A) 电流量测": "放电电流(A) 电流量测",
  "放电通讯电流 DischargingCurrent[mA,U2] ∈ 610mA ~ 1200mA": "放电通讯电流 DischargingCurrent[mA,U2] ∈ 610mA ~ 1200mA",
  "放电电源关闭": "放电电源关闭",
  "充电电压调整": "充电电压调整",
  "调整延时": "调整延时",
  "充电测试自检电流 电流量测": "充电测试自检电流 电流量测",
  "Cell&NTC Voltage[mV,U2] ∈ 7000mV ~ 7400mV": "Cell&NTC Voltage[mV,U2] ∈ 7000mV ~ 7400mV",
  "Cell&NTC BatteryFaults[U2] >= 0": "Cell&NTC BatteryFaults[U2] >= 0",

  "lowSpeedTestValue": "低档转速测试值",
  "mediumSpeedTestValue": "中档转速测试值",
  "highSpeedTestValue": "高档转速测试值",

  "转速结果": "转速结果",
  "直立结果": "直立结果",
  "未装滚刷结果": "未装滚刷结果",
  "未装污水桶结果": "未装污水桶结果",
  "污水桶满结果": "污水桶满结果",
  "WIFI连接结果": "WIFI连接结果",
  "WIFI语音结果": "WIFI语音结果",
  "污水桶未满结果": "污水桶未满结果",
  "主电机结果": "主电机结果",
  "清除日志结果": "清除日志结果",
  "SN码比较": "SN码比较",
  "通讯结果": "通讯结果",
  "转速上限": "转速上限",
  "转速下限": "转速下限",
  "SN码比较测试1不使用0使用": "SN码比较测试1不使用0使用",
  "倾斜转速测试1不使用0使用": "倾斜转速测试1不使用0使用",
  "真立到试1不使用0使用": "真立到试1不使用0使用",
  "未装滚刷测试1不使用0使用": "未装滚刷测试1不使用0使用",
  "未装污水桶测试1不使用0使用": "未装污水桶测试1不使用0使用",
  "污水桶满测试1不使用0使用": "污水桶满测试1不使用0使用",
  "WIFI按健1不使用0使用": "WIFI按健1不使用0使用",
  "堵转测试1不使用0使用": "堵转测试1不使用0使用",
  "清洁桶测试1不使用0使用": "清洁桶测试1不使用0使用",
  "主电机测试1不使用0使用": "主电机测试1不使用0使用",
  "清除日志测试1不使用0使用": "清除日志测试1不使用0使用",

  "是否复测0不复测1复测": "是否复测0不复测1复测",
  "排水结果": "排水结果",
  "SN码结果": "SN码结果",
  "无水检测结果": "无水检测结果",
  "排气检测结果": "排气检测结果",
  "低档流量结果": "低档流量结果",
  "高档流量结果": "高档流量结果",
  "电流结果": "电流结果",
  "有水结果": "有水结果",
  "倾斜结果": "倾斜结果",
  "低档试产结果": "低档试产结果",
  "高档试产结果": "高档试产结果",
  "无水检测使用0不使用1": "无水检测使用0不使用1",
  "低档流量使用0不使用1": "低档流量使用0不使用1",
  "倾斜使用0不使用1": "倾斜使用0不使用1",
  "高档流量使用0不使用1": "高档流量使用0不使用1",
  "排水使用使用0不使用1": "排水使用使用0不使用1",
  "有水检测使用0不使用1": "有水检测使用0不使用1",
  "电流检测使用0不使用1": "电流检测使用0不使用1",
  "低档试产使用0不使用1": "低档试产使用0不使用1",
  "高档试产使用0不使用1": "高档试产使用0不使用1",
  "低档流量上限": "低档流量上限",
  "低档流量下限": "低档流量下限",
  "高档流量上限": "高档流量上限",
  "高档流量下限": "高档流量下限",
  "电流上限": "电流上限",
  "电流下限": "电流下限",
  "低档试产上限": "低档试产上限",
  "低档试产下限": "低档试产下限",
  "高档试产上限": "高档试产上限",
  "高档试产下限": "高档试产下限",

  "充气压力": "充气压力",
  "保压压力": "保压压力",
  "泄气压力": "泄气压力",
  "低档真空度": "低档真空度",
  "高档真空度": "高档真空度",
  "充电电流": "充电电流",
  "充气压力上限": "充气压力上限",
  "充气压力下限": "充气压力下限",
  "保压压力上限": "保压压力上限",
  "保压压力下限": "保压压力下限",
  "泄气压力下限": "泄气压力下限",
  "低档真空度上限": "低档真空度上限",
  "低档真空度下限": "低档真空度下限",
  "高档真空度上限": "高档真空度上限",
  "高档真空度下限": "高档真空度下限",
  "功能按键": "功能按键",
  "开关按键": "开关按键",
  "清洁按键": "清洁按键",
  "WIFI按键": "WIFI按键",
  "语音检测": "语音检测",
  "充气压力测试1不使用0使用": "充气压力测试1不使用0使用",
  "保压压力测试1不使用0使用": "保压压力测试1不使用0使用",
  "泄压压力测试1不使用0使用": "泄压压力测试1不使用0使用",
  "低档真空度测试1不使用0使用": "低档真空度测试1不使用0使用",
  "高真空度测试1不使用0使用": "高真空度测试1不使用0使用",
  "充电电流测试1不使用0使用": "充电电流测试1不使用0使用",
  "功能按键测试1不使用0使用": "功能按键测试1不使用0使用",
  "开关按键测试1不使用0使用": "开关按键测试1不使用0使用",
  "清洁键测试1不使用0使用": "清洁键测试1不使用0使用",
  "WIFI键测试1不使用0使用": "WIFI键测试1不使用0使用",
  "电解水1不使用0使用": "电解水1不使用0使用",
  "语音1不使用使用": "语音1不使用使用",
  "HAPA测试": "HAPA测试",
  "通讯异常（10K 2NG）": "通讯异常（10K 2NG）",
  "复测结果（1复测0没有复测）": "复测结果（1复测0没有复测）",
  "电解水结果": "电解水结果",
  "电压上限": "电压上限",
  "电压下限": "电压下限",

  "地刷固定气缸": "地刷固定气缸",
  "通讯辅助气缸": "通讯辅助气缸",
  "读倾斜": "读倾斜",
  "写入主板类型": "写入主板类型",
  "读电池电压": "读电池电压",
  "读主机类型": "读主机类型",
  "读取wifi版本": "读取wifi版本",
  "读取wifi激活": "读取wifi激活",
  "写入wifi帐户名": "写入wifi帐户名",
  "写入wifi密码": "写入wifi密码",
  "连接wifi": "连接wifi",
  "清除wifi": "清除wifi",
  "读取wifi": "读取wifi",
  "地刷开": "地刷开",
  "堵转气缸（上下）": "堵转气缸（上下）",
  "编码器气缸": "编码器气缸",
  "编码器复位": "编码器复位",
  "编码器气缸回": "编码器气缸回",
  "编码器复位结束": "编码器复位结束",
  "堵转气缸（上下）回": "堵转气缸（上下）回",
  "堵断测试": "堵断测试",
  "地刷关": "地刷关",
  "读取电池包版本": "读取电池包版本",
  "读语音版本": "读语音版本",
  "写PumpHour": "写PumpHour",
  "读PumpHour": "读PumpHour",

  "配网按键": "配网按键",
  "配网键测试1不使用0使用": "配网键测试1不使用0使用",
  "通讯异常（1OK 2NG）": "通讯异常（1OK 2NG）",

  "通讯异常": "通讯异常",
  "90W真空度上限": "90W真空度上限",
  "90真空度下限": "90真空度下限",
  "躺平测试0使用/1不用": "躺平测试0使用/1不用",
  "70W真空度测试0使用/1不用": "70W真空度测试0使用/1不用",
  "90W真空度测试0使用/1不用": "90W真空度测试0使用/1不用",
  "充电电流测式0使用/1不用": "充电电流测式0使用/1不用",
  "70W真空度": "70W真空度",
  "躺平测试1OK/2NG": "躺平测试1OK/2NG",
  "清除日1OK/2NG": "清除日1OK/2NG",
  "70W真空度上限": "70W真空度上限",
  "70W真空度下限": "70W真空度下限",
  "充电电流上限": "充电电流上限",
  "充电电流下限": "充电电流下限",
  "90W真空度": "90W真空度",
  "x轴角度测试0使用/1不用": "x轴角度测试0使用/1不用",
  "Y轴角度测试0使用/1不用": "Y轴角度测试0使用/1不用",
  "X轴角度显示": "X轴角度显示",
  "Y轴角度显示": "Y轴角度显示",
  "x轴角度上限": "x轴角度上限",
  "x轴角度下限": "x轴角度下限",
  "Y轴角度下限": "Y轴角度下限",

  "电解水使用": "电解水使用",
  "电解水上限": "电解水上限",
  "电解水下限": "电解水下限",

  "直立测试态D410（1OK 2NG)": "直立测试态D410（1OK 2NG)",
  "反转转速": "反转转速",
  "反转转向（1OK 2NG)": "反转转向（1OK 2NG)",
  "正转转速": "正转转速",
  "正转转向（1OK2NG)": "正转转向（1OK2NG)",
  "反转负载电流": "反转负载电流",
  "正转负载电流": "正转负载电流",
  "污水桶水满（1OK 2NG)": "污水桶水满（1OK 2NG)",
  "堵转结果（1OK 2NG)": "堵转结果（1OK 2NG)",
  "清除日志（10K 2NG)": "清除日志（10K 2NG)",
  "堵转到试1不使用0用": "堵转到试1不使用0用",
  "清楚日志1不使用0使用": "清楚日志1不使用0使用",
  "直立测试1不使用0使用": "直立测试1不使用0使用",
  "反转转速测试1不使用0使用": "反转转速测试1不使用0使用",
  "反转转向测试1不使用0使用": "反转转向测试1不使用0使用",
  "正转转速测试1不使用0使用": "正转转速测试1不使用0使用",
  "正转转向测试1不使用0使用": "正转转向测试1不使用0使用",
  "反转负载电流1不使用0使用": "反转负载电流1不使用0使用",
  "正转负转电流1不使用0使用": "正转负转电流1不使用0使用",
  "污水桶水满1不使用0使用": "污水桶水满1不使用0使用",
  "反转转速上限": "反转转速上限",
  "反转转速下限": "反转转速下限",
  "反转负载电流上限": "反转负载电流上限",
  "反转负载电流下限": "反转负载电流下限",
  "正转转速上限": "正转转速上限",
  "正转转速下限": "正转转速下限",
  "正转负载电流上限": "正转负载电流上限",
  "正转负载电流下限": "正转负载电流下限",
  "有复测1无复测0": "有复测1无复测0",
  "通讯异常写2": "通讯异常写2",

  "气缸复位": "气缸复位",
  "垫脚测试": "垫脚测试",
  "产品通电板通电": "产品通电板通电",
  "烘干托盘电压检测": "烘干托盘电压检测",
  "请确认光栅遮挡": "请确认光栅遮挡",
  "气缸横移出": "气缸横移出",
  "产品通电&通讯板通电": "产品通电&通讯板通电",
  "气缸横移出到位检测": "气缸横移出到位检测",
  "产品通电&压紧": "产品通电&压紧",
  "风机开(100%)&继电器开": "风机开(100%)&继电器开",
  "PTC导通&NTC初始状态": "PTC导通&NTC初始状态",
  "充电MOS开": "充电MOS开",
  "电压测试继电器吸合": "电压测试继电器吸合",
  "电压检测": "电压检测",
  "充电MOS关": "充电MOS关",
  "霍尔检测": "霍尔检测",
  "风机开(100%)": "风机开(100%)",
  "风机电流&风量": "风机电流&风量",
  "NTC升温&NTC功率": "NTC升温&NTC功率",
  "PTC继电器关&风机关": "PTC继电器关&风机关",
  "压紧气缸复位": "压紧气缸复位",
  "继电器复位": "继电器复位",

  "产品通电(30V)": "产品通电(30V)",
  "地刷压紧气缸出": "地刷压紧气缸出",
  "产品固定气缸出": "产品固定气缸出",
  "静至1S": "静至1S",
  "进入测试模式": "进入测试模式",
  "陀螺仪读取": "陀螺仪读取",
  "读陀螺仪Type": "读陀螺仪Type",
  "读取产品陀螺仪": "读取产品陀螺仪",
  "产品陀螺仪标定": "产品陀螺仪标定",
  "等待延时5S": "等待延时5S",

  "SetBaudsFinish": "SetBaudsFinish",
  "磁铁检测": "磁铁检测",
  "固定地刷&机身气缸": "固定地刷&机身气缸",
  "通讯通电": "通讯通电",
  "获取UID": "获取UID",
  "获取SN密码": "获取SN密码",
  "水泵开(75g)": "水泵开(75g)",
  "读电芯差值": "读电芯差值",
  "主电机开(120W)": "主电机开(120W)",
  "开始连接wifi": "开始连接wifi",
  "查询wifi": "查询wifi",
  "躺平测试": "躺平测试",
  "倾斜测试": "倾斜测试",
  "灰尘接收强度前": "灰尘接收强度前",
  "灰尘气缸（前后）": "灰尘气缸（前后）",
  "灰尘气缸（左右）": "灰尘气缸（左右）",
  "灰尘气缸（上下）": "灰尘气缸（上下）",
  "灰尘接收强度遮挡": "灰尘接收强度遮挡",
  "灰尘气缸（上下）回": "灰尘气缸（上下）回",
  "灰尘气缸（左右）回": "灰尘气缸（左右）回",
  "灰尘气缸（前后）回": "灰尘气缸（前后）回",
  "检测电池包加密": "检测电池包加密",
  "读取电池包固件": "读取电池包固件",
  "写入语音型号": "写入语音型号",
  "读取语音型号": "读取语音型号",
  "无水检测": "无水检测",
  "电机转速": "电机转速",
  "主电机关": "主电机关",
  "掉电模式": "掉电模式",
  "气缸复位1": "气缸复位1",
  "倾斜模式": "倾斜模式",
  "屏幕全橙": "屏幕全橙",
  "屏幕全橙灯环": "屏幕全橙灯环",
  "污水桶未满": "污水桶未满",
  "电池包标示信息识别": "电池包标示信息识别",
  "低档真空": "低档真空",
  "中档真空": "中档真空",
  "高档真空": "高档真空",
  "转速": "转速",
  "转向（1=0K/2=NG）": "转向（1=0K/2=NG）",
  "堵转（1=0K/2=NG）": "堵转（1=0K/2=NG）",
  "低档真空上限": "低档真空上限",
  "低档真空下限": "低档真空下限",
  "中档真空上限": "中档真空上限",
  "中档真空下限": "中档真空下限",
  "高档真空上限": "高档真空上限",
  "转速测试1不使用0使用": "转速测试1不使用0使用",
  "转向测试1不使用0使用": "转向测试1不使用0使用",
  "低档测试1不使用0使用": "低档测试1不使用0使用",
  "中档测试1不使用0使用": "中档测试1不使用0使用",
  "高档测试1不使用0使用": "高档测试1不使用0使用",
  "左贴边电流": "左贴边电流",
  "非贴边电流": "非贴边电流",
  "右贴边电流": "右贴边电流",
  "地毯测试": "地毯测试",
  "地板测试": "地板测试",
  "左贴边电流上限": "左贴边电流上限",
  "左贴边电流下限": "左贴边电流下限",
  "非贴边电流上限": "非贴边电流上限",
  "非贴边电流下限": "非贴边电流下限",
  "左贴边测试（0使用1不使用）": "左贴边测试（0使用1不使用）",
  "非贴边测试（0使用1不使用）": "非贴边测试（0使用1不使用）",
  "地毯测试（0使用1不使用）": "地毯测试（0使用1不使用）",
  "地板测试（0使用1不使用）": "地板测试（0使用1不使用）",
  "右贴边电流上限": "右贴边电流上限",
  "右贴边电流下限": "右贴边电流下限",
  "地毯转速上限": "地毯转速上限",
  "地毯转速下限": "地毯转速下限",
  "地板转速上限": "地板转速上限",
  "地板转速下限": "地板转速下限",
  "气缸夹紧(下)": "气缸夹紧(下)",
    "整机&通讯板通电": "整机&通讯板通电",
    "基站进入测试模式": "基站进入测试模式",
    "读电源版本号": "读电源版本号",
    "读机头控制板本号": "读机头控制板本号",
    "屏幕全开": "屏幕全开",
    "屏幕测试": "屏幕测试",
    "整机霍尔检测(无)": "整机霍尔检测(无)",
    "自清洁键释放": "自清洁键释放",
    "自清洁键按下": "自清洁键按下",
    "磁铁气缸出": "磁铁气缸出",
    "整机霍尔检测(有)": "整机霍尔检测(有)",
    "SN写入(基站)": "SN写入(基站)",
    "SN读取(基站)": "SN读取(基站)",
    "基站清除日志": "基站清除日志",
    "基站进入正常模式": "基站进入正常模式",
    "整机&通讯板断电": "整机&通讯板断电",
    "电压判断": "电压判断",
    "样品通电": "样品通电",
    "请安装13孔堵头": "请安装13孔堵头",
    "启动AC电机": "启动AC电机",
    "基站加手持13孔真空度(宠物)": "基站加手持13孔真空度(宠物)",
    "基站加手持13孔真空度": "基站加手持13孔真空度",
    "请将堵头取下": "请将堵头取下",
    "关闭AC电机": "关闭AC电机",
    "开始充电": "开始充电",
    "充电电压": "充电电压",
    "清除基站日志": "清除基站日志",
    "进入正常模式": "进入正常模式",
    "SN码比较测试结果": "SN码比较测试结果",
    "分道堵塞结果": "分道堵塞结果",
    "语音测试结果": "语音测试结果",
    "全开功率结果": "全开功率结果",
    "13孔真空度结果": "13孔真空度结果",
    "压力传感器结果": "压力传感器结果",
    "13孔真空度上限": "13孔真空度上限",
    "13孔真空度下限": "13孔真空度下限",
    "语音测试上限": "语音测试上限",
    "语音测试下限": "语音测试下限",
    "全开功率上限": "全开功率上限",
    "全开功率下限": "全开功率下限",
    "13孔真空度测试使用1不使用0使用": "13孔真空度测试使用1不使用0使用",
    "语音测试测试使用1不使用0使用": "语音测试测试使用1不使用0使用",
    "分道堵塞测试使用1不使用0使用": "分道堵塞测试使用1不使用0使用",
    "全开功率使用1不使用0使用": "全开功率使用1不使用0使用",
    "压力检测使用1不使用0使用": "压力检测使用1不使用0使用",

    "复位开始": "复位开始",
    "复位结束": "复位结束",
    "真空度初始值": "真空度初始值",
    "RTC初始化": "RTC初始化",
    "Delay 200ms": "Delay 200ms",
    "烧录信息完整测试": "烧录信息完整测试",
    "测试程序版本": "测试程序版本",
    "测试项目名称": "测试项目名称",
    "按键OFF": "按键OFF",
    "滚筒安装": "滚筒安装",
    "滚筒外扩电机复位": "滚筒外扩电机复位",
    "启动滚筒拖地组件正转": "启动滚筒拖地组件正转",
    "接水盘安装": "接水盘安装",
    "污水箱安装": "污水箱安装",
    "0°陀螺仪测试": "0°陀螺仪测试",
    "启动风机": "启动风机",
    "启动污水泵": "启动污水泵",
    "Delay 1000ms": "Delay 1000ms",
    "滚筒外扩电机状态-未外扩": "滚筒外扩电机状态-未外扩",
    "滚筒下降状态": "滚筒下降状态",
    "外扩码盘归位状态": "外扩码盘归位状态",
    "真空度测试": "真空度测试",
    "撞板左伸出": "撞板左伸出",
    "撞板右伸出": "撞板右伸出",
    "撞板ON": "撞板ON",
    "撞板右缩回": "撞板右缩回",
    "撞板左缩回": "撞板左缩回",
    "Delay500ms": "Delay500ms",
    "风机转速": "风机转速",
    "停止吸尘电机": "停止吸尘电机",
    "电池电压": "电池电压",
    "电池电量": "电池电量",
    "电池温度": "电池温度",
    "启动滚刷": "启动滚刷",
    "上升触发": "上升触发",
    "边刷转动": "边刷转动",
    "Delay 2000ms": "Delay 2000ms",
    "右边刷电流值": "右边刷电流值",
    "启动滚筒电机外扩到最外位置": "启动滚筒电机外扩到最外位置",
    "Delay 500ms": "Delay 500ms",
    "跌落—OFF": "跌落—OFF",
    "污水箱低水位": "污水箱低水位",
    "Delay 3000ms": "Delay 3000ms",
    "滚筒外扩电机状态": "滚筒外扩电机状态",
    "外扩码盘状态": "外扩码盘状态",
    "复位电机外扩": "复位电机外扩",
    "滚筒外扩电机归位状态": "滚筒外扩电机归位状态",
    "滚筒未抬升状态": "滚筒未抬升状态",
    "滚刷电流": "滚刷电流",
    "滚刷停止": "滚刷停止",
    "停边刷": "停边刷",
    "启动滚筒抬升": "启动滚筒抬升",
    "启动驱动轮左": "启动驱动轮左",
    "启动驱动轮右": "启动驱动轮右",
    "左后下视（无反射）": "左后下视（无反射）",
    "左下视（无反射）": "左下视（无反射）",
    "左前下视（无反射）": "左前下视（无反射）",
    "右前下视（无反射）": "右前下视（无反射）",
    "右下视（无反射）": "右下视（无反射）",
    "旋转动作": "旋转动作",
    "90°旋转到位检测": "90°旋转到位检测",
    "Delay 1500ms": "Delay 1500ms",
    "90°陀螺仪测试": "90°陀螺仪测试",
    "旋转恢复": "旋转恢复",
    "驱动轮左转速": "驱动轮左转速",
    "左驱动轮电流值": "左驱动轮电流值",
    "停驱动轮左": "停驱动轮左",
    "驱动轮右转速": "驱动轮右转速",
    "右驱动轮电流值": "右驱动轮电流值",
    "停驱动轮右": "停驱动轮右",
    "上升复位": "上升复位",
    "是否带超声波": "是否带超声波",
    "滚筒组件电流": "滚筒组件电流",
    "停止滚筒组件": "停止滚筒组件",
    "滚筒抬升状态": "滚筒抬升状态",
    "退出测试模式": "退出测试模式",
    "TCP连接检测": "TCP连接检测",
    "Delay 8000ms": "Delay 8000ms",
    "系统信息获取": "系统信息获取",
    "ARM端 固件版本": "ARM端 固件版本",
    "SN比对": "SN比对",
    "匹配PWD": "匹配PWD",
    "MAC地址": "MAC地址",
    "语言查询": "语言查询",
    "国家查询": "国家查询",
    "DID": "DID",
    "type": "type",
    "password": "password",
    "设备lb": "设备lb",
    "时间设置": "时间设置",
    "时区检测": "时区检测",
    "wifi_efuse检查": "wifi_efuse检查",
    "系统信息plus获取": "系统信息plus获取",
    "lds_ver": "lds_ver",
    "Carpet": "Carpet",
    "Map": "Map",
    "bat": "bat",
    "fan": "fan",
    "pump": "pump",
    "iot": "iot",
    "Simple": "Simple",
    "smart_type": "smart_type",
    "ssidPrefix": "ssidPrefix",
    "wheeltype": "wheeltype",
    "ssidPrefixForStation": "ssidPrefixForStation",
    "station": "station",
    "ozmo": "ozmo",
    "aivi": "aivi",
    "sl": "sl",
    "swb": "swb",
    "erp": "erp",
    "sewDetc": "sewDetc",
    "dry": "dry",
    "hot": "hot",
    "yiko": "yiko",
    "ExSideBr": "ExSideBr",
    "dywash": "dywash",
    "autoCA": "autoCA",
    "station_suffix": "station_suffix",
    "wificlose": "wificlose",

    "固定气缸下压": "固定气缸下压",
    "注水口气缸伸出": "注水口气缸伸出",
    "溢气口电磁阀关闭": "溢气口电磁阀关闭",
    "溢水口电磁阀关闭": "溢水口电磁阀关闭",
    "超声组件电磁阀关闭": "超声组件电磁阀关闭",
    "吸污口电磁阀关闭": "吸污口电磁阀关闭",
    "工装气泵电磁阀关闭": "工装气泵电磁阀关闭",
    "工装气泵关闭": "工装气泵关闭",
    "自动扫码": "自动扫码",
    "工装气泵打开": "工装气泵打开",
    "启动清水泵": "启动清水泵",
    "关闭污水泵": "关闭污水泵",
    "Delay 300ms": "Delay 300ms",
    "读取出水口气压值_保压前": "读取出水口气压值_保压前",
    "关闭清水泵": "关闭清水泵",
    "读取注水口气压_保压前": "读取注水口气压_保压前",
    "读取溢水口气压_保压前": "读取溢水口气压_保压前",
    "读取溢气口气压值_保压前": "读取溢气口气压值_保压前",
    "读取吸污口气压值_保压前": "读取吸污口气压值_保压前",
    "读注水口气压_保压后": "读注水口气压_保压后",
    "读取溢水口气压_保压后": "读取溢水口气压_保压后",
    "读取溢气口气压值_保压后": "读取溢气口气压值_保压后",
    "读取吸污口气压值_保压后": "读取吸污口气压值_保压后",
    "读注水口气压差值": "读注水口气压差值",
    "读溢水口气压差值": "读溢水口气压差值",
    "读溢气口气压差值": "读溢气口气压差值",
    "读取吸污口气压差值": "读取吸污口气压差值",
    "溢气口电磁阀打开": "溢气口电磁阀打开",
    "吸污口电磁阀打开": "吸污口电磁阀打开",
    "出水口电磁阀关闭": "出水口电磁阀关闭",
    "固定气缸抬升": "固定气缸抬升",
    "复位注水口气缸": "复位注水口气缸",

    "设置基站类型-开普勒": "设置基站类型-开普勒",
    "夹紧气缸动作": "夹紧气缸动作",
    "固定气缸动作": "固定气缸动作",
    "下压气缸动作": "下压气缸动作",
    "等待下压气缸到位": "等待下压气缸到位",
    "基站全相测试1": "基站全相测试1",
    "夹紧气缸重置": "夹紧气缸重置",
    "前进气缸动作": "前进气缸动作",
    "等待前进气缸到位": "等待前进气缸到位",
    "底座磁铁触发": "底座磁铁触发",
    "建立通讯": "建立通讯",
    "尘袋检测": "尘袋检测",
    "光耦在位": "光耦在位",
    "底座在位检测": "底座在位检测",
    "无清水箱检测": "无清水箱检测",
    "无污水箱检测": "无污水箱检测",
    "硬件检测-水箱": "硬件检测-水箱",
    "底座磁铁重置": "底座磁铁重置",
    "空载功率": "空载功率",
    "软件版本基站类型": "软件版本基站类型",
    "烧录校验值": "烧录校验值",
    "SN写入读取": "SN写入读取",
    "灯效确认": "灯效确认",
    "关闭污水检测红绿灯": "关闭污水检测红绿灯",
    "读取绿光关闭值": "读取绿光关闭值",
    "读取红外光关闭值": "读取红外光关闭值",
    "打开污水检测红绿灯": "打开污水检测红绿灯",
    "读取绿光打开值": "读取绿光打开值",
    "读取红外光打开值": "读取红外光打开值",
    "顶杆电机上升堵转电流读取": "顶杆电机上升堵转电流读取",
    "顶杆电机下降电流读取": "顶杆电机下降电流读取",
    "设置电磁阀打开": "设置电磁阀打开",
    "设置清水泵打开": "设置清水泵打开",
    "注水口水路检测": "注水口水路检测",
    "设置清水泵关闭": "设置清水泵关闭",
    "下压气缸重置-泄气": "下压气缸重置-泄气",
    "磁铁下压气缸动作": "磁铁下压气缸动作",
    "抬升气缸动作": "抬升气缸动作",
    "设置电磁阀关闭": "设置电磁阀关闭",
    "洗抹布水路检测1": "洗抹布水路检测1",
    "洗抹布水路检测2": "洗抹布水路检测2",
    "清水箱至蠕动泵水路检测": "清水箱至蠕动泵水路检测",
    "清水箱检测": "清水箱检测",
    "污水箱检测": "污水箱检测",
    "底座默认检测": "底座默认检测",
    "设置污水泵打开": "设置污水泵打开",
    "吸污水水路检测1": "吸污水水路检测1",
    "吸污水水路检测2": "吸污水水路检测2",
    "设置污水泵关闭": "设置污水泵关闭",
    "集尘打开": "集尘打开",
    "吸尘风机功率": "吸尘风机功率",
    "关闭集尘": "关闭集尘",
    "打开风机": "打开风机",
    "读取烘干风机功率": "读取烘干风机功率",
    "打开加热丝": "打开加热丝",
    "等待PTC功率稳定": "等待PTC功率稳定",
    "读取PTC功率": "读取PTC功率",
    "关闭风机": "关闭风机",
    "关闭加热丝": "关闭加热丝",
    "加热水温度初始值": "加热水温度初始值",
    "设置加热水模块打开": "设置加热水模块打开",
    "加热模块功率": "加热模块功率",
    "设置加热水模块关闭": "设置加热水模块关闭",
    "打开充电": "打开充电",
    "打开充电开关": "打开充电开关",
    "充电电压检测": "充电电压检测",
    "充电电流读取": "充电电流读取",
    "关闭充电开关": "关闭充电开关",
    "气缸重置": "气缸重置",
    "等待复位结束": "等待复位结束",
    "基站全相测试2": "基站全相测试2",
    "固定气缸重置": "固定气缸重置",
    "Delay 5000ms": "Delay 5000ms",
    "复位检测": "复位检测",
    "工位号": "工位号",
  "产品型号": "产品型号",
  "档位": "档位",
  "二维码": "二维码",
  "电压": "电压",
  "电流": "电流",
  "功率": "功率",
  "功率上限": "功率上限",
  "功率下限": "功率下限",
  "风压": "风压",
  "风压上限": "风压上限",
  "风压下限": "风压下限",
  "加速度": "加速度",
  "加速度上限": "加速度上限",
  "加速度下限": "加速度下限",
  "速度": "速度",
  "速度上限": "速度上限",
  "速度下限": "速度下限",
  "位移": "位移",
  "位移上限": "位移上限",
  "位移下限": "位移下限",
  "振动频带1": "振动频带1",
  "振动频带1上限": "振动频带1上限",
  "振动频带1下限": "振动频带1下限",
  "振动频带2": "振动频带2",
  "振动频带2上限": "振动频带2上限",
  "振动频带2下限": "振动频带2下限",
  "振动频带3": "振动频带3",
  "振动频带3上限": "振动频带3上限",
  "振动频带3下限": "振动频带3下限",
  "振动频带4": "振动频带4",
  "振动频带4上限": "振动频带4上限",
  "振动频带4下限": "振动频带4下限",
  "振动频带5": "振动频带5",
  "振动频带5上限": "振动频带5上限",
  "振动频带5下限": "振动频带5下限",
  "振动频带6": "振动频带6",
  "振动频带6上限": "振动频带6上限",
  "振动频带6下限": "振动频带6下限",
  "噪音": "噪音",
  "噪音上限": "噪音上限",
  "噪音下限": "噪音下限",
  "噪音频带1": "噪音频带1",
  "噪音频带1上限": "噪音频带1上限",
  "噪音频带1下限": "噪音频带1下限",
  "噪音频带2": "噪音频带2",
  "噪音频带2上限": "噪音频带2上限",
  "噪音频带2下限": "噪音频带2下限",
  "噪音频带3": "噪音频带3",
  "噪音频带3上限": "噪音频带3上限",
  "噪音频带3下限": "噪音频带3下限",
  "噪音频带4": "噪音频带4",
  "噪音频带4上限": "噪音频带4上限",
  "噪音频带4下限": "噪音频带4下限",
  "噪音频带5": "噪音频带5",
  "噪音频带5上限": "噪音频带5上限",
  "噪音频带5下限": "噪音频带5下限",
  "噪音频带6": "噪音频带6",
  "噪音频带6上限": "噪音频带6上限",
  "噪音频带6下限": "噪音频带6下限",
  "耗时": "耗时",
  "日期": "日期",
  "结果": "结果",
  "后加全开电压": "后加全开电压",
  "后加全开电流": "后加全开电流",
  "后加全开功率": "后加全开功率",
  "后加全开真空": "后加全开真空",
  "全开电流": "全开电流",
  "全开功率": "全开功率",
  "全开真空": "全开真空",
  "全堵电流": "全堵电流",
  "全堵功率": "全堵功率",
  "全堵真空": "全堵真空",
  "清水桶保压压力": "清水桶保压压力",
  "地刷转动判定": "地刷转动判定",
  "压紧气缸": "压紧气缸",
  "假包气缸": "假包气缸",
  "通讯板通电": "通讯板通电",
  "全蓝检测": "全蓝检测",
  "屏幕全亮": "屏幕全亮",
  "全红检测": "全红检测",
  "挡位切换按钮按下": "挡位切换按钮按下",
  "挡位切换气缸": "挡位切换气缸",
  "通讯板断电": "通讯板断电",
  "全开孔/高速/电压": "全开孔/高速/电压",
  "全开孔/高速/功率": "全开孔/高速/功率",
  "全开孔/高速/流量": "全开孔/高速/流量"
}
