{
    "code": 200,
    "data": [
        {
            "_id": "6913d4dd46c928c04cbf2e1e",
            "barcode": "1101101001-000001",
            "relatedBill": "",
            "productLineId": "67582bc0eebf2a4b34951ef6",
            "productLineName": "面罩主机1号线",
            "materialId": "6757964a354604091e6fd8f4",
            "materialCode": "1101101001",
            "materialName": "B082 吸尘器M08230RED",
            "materialSpec": "120V 4A 60Hz   YDC54",
            "isProduct": true,
            "businessType": "2",
            "craftId": "6757eac9ba793f475104f963",
            "craftVersion": "",
            "status": "IN_PROCESS",
            "productStatus": "REPAIRING",
            "progress": 80,
            "startTime": "2025-11-12T00:29:17.880Z",
            "processNodes": [
                {
                    "nodeId": "9b0e647f-d461-470e-8fb8-2cdf327ed49d",
                    "nodeType": "MATERIAL",
                    "materialId": "6757964a354604091e6fd8f4",
                    "materialCode": "1101101001",
                    "materialName": "B082 吸尘器M08230RED",
                    "materialSpec": "120V 4A 60Hz   YDC54",
                    "isPackingBox": false,
                    "batchDocRequired": false,
                    "batchDocNumber": "",
                    "craftId": "6757eac9ba793f475104f963",
                    "craftName": "检验设备测试工艺A",
                    "level": 0,
                    "requireScan": false,
                    "scanOperation": false,
                    "isComponent": false,
                    "isKeyMaterial": false,
                    "isBatch": false,
                    "batchQuantity": 0,
                    "isRfid": false,
                    "barcode": "",
                    "relatedBill": "",
                    "barcodeType": "",
                    "scanTime": null,
                    "status": "PENDING",
                    "endTime": null,
                    "updateBy": null
                },
                {
                    "nodeId": "cb6c3810-fbeb-49c7-9546-506069010f0f",
                    "nodeType": "PROCESS_STEP",
                    "isPackingBox": false,
                    "processStepId": "6772066a2ee7d6f3af6ccc9f",
                    "processName": "添可测试工序1",
                    "processCode": "A_C_0001",
                    "processSort": 1,
                    "originalSort": 1,
                    "processType": "C",
                    "batchDocRequired": false,
                    "batchDocNumber": "",
                    "craftId": "6757eac9ba793f475104f963",
                    "craftName": "检验设备测试工艺A",
                    "level": 1,
                    "parentNodeId": "9b0e647f-d461-470e-8fb8-2cdf327ed49d",
                    "requireScan": true,
                    "scanOperation": false,
                    "isComponent": false,
                    "isKeyMaterial": false,
                    "isBatch": false,
                    "batchQuantity": 0,
                    "isRfid": false,
                    "barcode": "",
                    "relatedBill": "",
                    "barcodeType": "",
                    "scanTime": null,
                    "status": "COMPLETED",
                    "endTime": "2025-12-17T08:15:07.750Z",
                    "updateBy": "6589464152762736ca434000"
                },
                {
                    "nodeId": "37ab7d3a-81e1-442e-90fb-2490e708a3bd",
                    "nodeType": "PROCESS_STEP",
                    "isPackingBox": false,
                    "processStepId": "6911fe7b6b04a7334bf3c8a5",
                    "processName": "装箱工序",
                    "processCode": "A_E_0001",
                    "processSort": 2,
                    "originalSort": 2,
                    "processType": "E",
                    "batchDocRequired": false,
                    "batchDocNumber": "",
                    "craftId": "6757eac9ba793f475104f963",
                    "craftName": "检验设备测试工艺A",
                    "level": 1,
                    "parentNodeId": "9b0e647f-d461-470e-8fb8-2cdf327ed49d",
                    "requireScan": true,
                    "scanOperation": false,
                    "isComponent": false,
                    "isKeyMaterial": false,
                    "isBatch": false,
                    "batchQuantity": 0,
                    "isRfid": false,
                    "barcode": "",
                    "relatedBill": "",
                    "barcodeType": "",
                    "status": "COMPLETED",
                    "endTime": "2025-12-17T08:15:48.316Z",
                    "updateBy": "6589464152762736ca434000"
                },
                {
                    "nodeId": "7ae9c9a2-2d70-4008-ab88-87210658e8ae",
                    "nodeType": "PROCESS_STEP",
                    "isPackingBox": false,
                    "processStepId": "6772090ecd38e2f57061bf68",
                    "processName": "添可工序测试6",
                    "processCode": "A_A_0005",
                    "processSort": 3,
                    "originalSort": 3,
                    "processType": "F",
                    "batchDocRequired": false,
                    "batchDocNumber": "",
                    "craftId": "6757eac9ba793f475104f963",
                    "craftName": "检验设备测试工艺A",
                    "level": 1,
                    "parentNodeId": "9b0e647f-d461-470e-8fb8-2cdf327ed49d",
                    "requireScan": true,
                    "scanOperation": false,
                    "isComponent": false,
                    "isKeyMaterial": false,
                    "isBatch": false,
                    "batchQuantity": 0,
                    "isRfid": false,
                    "barcode": "",
                    "relatedBill": "",
                    "barcodeType": "",
                    "status": "PENDING"
                },
                {
                    "nodeId": "c3c92814-a6b8-4e2a-a445-1f0c0f7e5052",
                    "nodeType": "MATERIAL",
                    "materialId": "6757964a354604091e6fd8f6",
                    "materialCode": "1101102002",
                    "materialName": "B060 SD20505 吸尘器（4个装）",
                    "materialSpec": "120V 10A 60Hz  YDC50-1-9",
                    "materialQuantity": 1,
                    "materialUnit": "个",
                    "isPackingBox": true,
                    "batchDocRequired": false,
                    "batchDocNumber": "",
                    "craftId": "6757eac9ba793f475104f963",
                    "craftName": "检验设备测试工艺A",
                    "level": 2,
                    "parentNodeId": "37ab7d3a-81e1-442e-90fb-2490e708a3bd",
                    "requireScan": true,
                    "scanOperation": true,
                    "isComponent": false,
                    "isKeyMaterial": false,
                    "isBatch": true,
                    "batchQuantity": 2,
                    "isRfid": false,
                    "barcode": "1101102002-001",
                    "relatedBill": "001",
                    "barcodeType": "",
                    "scanTime": "2025-12-17T08:15:48.365Z",
                    "status": "COMPLETED",
                    "endTime": "2025-12-17T08:15:48.365Z",
                    "updateBy": "6589464152762736ca434000"
                },
                {
                    "nodeId": "f8eaf092-1b81-4cdb-89ed-02f256a2fde2",
                    "nodeType": "MATERIAL",
                    "materialId": "6757964a354604091e6fd900",
                    "materialCode": "1101103005",
                    "materialName": "B030 DUUD20120 吸尘器",
                    "materialSpec": "120V 7A 60Hz",
                    "materialQuantity": 1,
                    "materialUnit": "个",
                    "isPackingBox": false,
                    "batchDocRequired": false,
                    "batchDocNumber": "",
                    "craftId": "6757eac9ba793f475104f963",
                    "craftName": "检验设备测试工艺A",
                    "level": 2,
                    "parentNodeId": "cb6c3810-fbeb-49c7-9546-506069010f0f",
                    "requireScan": true,
                    "scanOperation": true,
                    "isComponent": false,
                    "isKeyMaterial": false,
                    "isBatch": true,
                    "batchQuantity": 5,
                    "isRfid": false,
                    "barcode": "1101103005-000001",
                    "relatedBill": "000001",
                    "barcodeType": "",
                    "scanTime": "2025-12-17T08:15:07.820Z",
                    "status": "COMPLETED",
                    "endTime": "2025-12-17T08:15:07.820Z",
                    "updateBy": "6589464152762736ca434000"
                }
            ],
            "productionPlanWorkOrderId": "6881d6f88557fa054a7fe832",
            "createAt": "2025-11-12T00:29:17.898Z",
            "updateAt": "2025-12-17T08:16:16.024Z",
            "__v": 6,
            "endTime": null,
            "updateBy": "6589464152762736ca434000"
        }
    ]
}